{"id":"gen8ou-1669546695","p1":"skibsthekid","p2":"misplayin","format":"gen8ou","log":"|j|\u2606skibsthekid\n|j|\u2606misplayin\n|t:|1664061778\n|gametype|singles\n|player|p1|skibsthekid|lady-gen4|\n|player|p2|misplayin|bugsy|\n|teamsize|p1|6\n|teamsize|p2|6\n|gen|8\n|tier|[Gen 8] OU\n|rule|Sleep Clause Mod: Limit one foe put to sleep\n|rule|Species Clause: Limit one of each Pok\u00e9mon\n|rule|OHKO Clause: OHKO moves are banned\n|rule|Evasion Items Clause: Evasion items are banned\n|rule|Evasion Moves Clause: Evasion moves are banned\n|rule|Endless Battle Clause: Forcing endless battles is banned\n|rule|HP Percentage Mod: HP is shown in percentages\n|rule|Dynamax Clause: You cannot dynamax\n|clearpoke\n|poke|p1|Zapdos|\n|poke|p1|Weavile, M|\n|poke|p1|Kartana|\n|poke|p1|Landorus-Therian, M|\n|poke|p1|Volcanion|\n|poke|p1|Diggersby, M|\n|poke|p2|Volcanion|\n|poke|p2|Garchomp, M|\n|poke|p2|Buzzwole|\n|poke|p2|Corviknight, F|\n|poke|p2|Zapdos-Galar|\n|poke|p2|Tapu Koko|\n|teampreview\n|inactive|Battle timer is ON: inactive players will automatically lose when time's up. (requested by skibsthekid)\n|inactive|misplayin also wants the timer to be on.\n|c|\u2606misplayin|gl gl\n|c|\u2606skibsthekid|you too\n|j| Rubiaa\n|j| UnstoppableUg\n|inactive|skibsthekid has 270 seconds left.\n|inactive|misplayin has 270 seconds left.\n|c| UnstoppableUg|Got the music playing while I'm preparing my dogs food LOL\n|inactive|skibsthekid has 240 seconds left.\n|c| Rubiaa|UnstoppableUg what music u playing?\n|c|\u2606misplayin|wait ima starting playing some kanye\n|c|\u2606misplayin|no way ima lose\n|\n|t:|1664061848\n|start\n|switch|p1a: Zapdos|Zapdos|100\/100\n|switch|p2a: Zapdos|Zapdos-Galar|100\/100\n|turn|1\n|c| UnstoppableUg|The legendary Tour theme Rubi\n|c| Rubiaa|oh, aight\n|\n|t:|1664061862\n|switch|p2a: Garchomp|Garchomp, M|100\/100\n|move|p1a: Zapdos|Hurricane|p2a: Garchomp\n|-damage|p2a: Garchomp|61\/100\n|-start|p2a: Garchomp|confusion\n|\n|-heal|p2a: Garchomp|67\/100|[from] item: Leftovers\n|upkeep\n|turn|2\n|c| Rubiaa|UnstoppableUg tell mauwi he or she's a W\n|c| UnstoppableUg|From Raisi K\n|c| UnstoppableUg|Will do and it's a he\n|c| Rubiaa|oh aight\n|inactive|skibsthekid has 270 seconds left.\n|inactive|skibsthekid has 240 seconds left.\n|c| UnstoppableUg|Swear, Jay, Techno and Laid all love Volcanion\n|c| UnstoppableUg|So\n|c| Rubiaa|bro technos team is a sample, just diggersby over melmetal LOL\n|c| UnstoppableUg|Lmao\n|c| UnstoppableUg|Fire team\n|c|\u2606skibsthekid|bro are you serious\n|c| Rubiaa|im being so fr\n|inactive|skibsthekid has 210 seconds left.\n|c|\u2606misplayin|lamoooo\n|c|\u2606misplayin|lmaoo*\n|c|\u2606skibsthekid|i asked a friend to send me teams and she sent me samples\n|c| Rubiaa|lamoooo\n|c|\u2606skibsthekid|not like this\n|c| UnstoppableUg|LOOOOOOL\n|c|\u2606misplayin|hold up bout to search this up\n|c| UnstoppableUg|it's a fire team tho\n|c| UnstoppableUg|LMAO\n|c| Rubiaa|it is\n|inactive|skibsthekid has 180 seconds left.\n|c| UnstoppableUg|Oh no he's gonna get scouted \ud83d\ude2d\ud83d\ude2d\n|c|\u2606misplayin|lmaoooo\n|c|\u2606misplayin|dwdw i wont\n|\n|t:|1664062008\n|switch|p1a: Weavile|Weavile, M|100\/100\n|-ability|p1a: Weavile|Pressure\n|-activate|p2a: Garchomp|confusion\n|move|p2a: Garchomp|Protect||[still]\n|-fail|p2a: Garchomp\n|\n|-heal|p2a: Garchomp|73\/100|[from] item: Leftovers\n|upkeep\n|turn|3\n|\n|t:|1664062012\n|switch|p2a: Buzzwole|Buzzwole|100\/100\n|move|p1a: Weavile|Beat Up|p2a: Buzzwole\n|-resisted|p2a: Buzzwole\n|-damage|p2a: Buzzwole|97\/100\n|-resisted|p2a: Buzzwole\n|-damage|p2a: Buzzwole|94\/100\n|-resisted|p2a: Buzzwole\n|-damage|p2a: Buzzwole|90\/100\n|-resisted|p2a: Buzzwole\n|-damage|p2a: Buzzwole|86\/100\n|-resisted|p2a: Buzzwole\n|-damage|p2a: Buzzwole|83\/100\n|-resisted|p2a: Buzzwole\n|-damage|p2a: Buzzwole|81\/100\n|-hitcount|p2a: Buzzwole|6\n|\n|upkeep\n|turn|4\n|\n|t:|1664062016\n|switch|p1a: Volcanion|Volcanion|100\/100\n|move|p2a: Buzzwole|Toxic|p1a: Volcanion\n|-status|p1a: Volcanion|tox\n|\n|-damage|p1a: Volcanion|95\/100 tox|[from] psn\n|upkeep\n|turn|5\n|inactive|skibsthekid has 180 seconds left.\n|\n|t:|1664062025\n|switch|p1a: Zapdos|Zapdos|100\/100\n|switch|p2a: Garchomp|Garchomp, M|73\/100\n|\n|-heal|p2a: Garchomp|80\/100|[from] item: Leftovers\n|upkeep\n|turn|6\n|\n|t:|1664062030\n|switch|p1a: Landorus|Landorus-Therian, M|100\/100\n|-ability|p1a: Landorus|Intimidate|boost\n|-unboost|p2a: Garchomp|atk|1\n|move|p2a: Garchomp|Toxic|p1a: Landorus\n|-status|p1a: Landorus|tox\n|\n|-heal|p2a: Garchomp|86\/100|[from] item: Leftovers\n|-damage|p1a: Landorus|94\/100 tox|[from] psn\n|upkeep\n|turn|7\n|\n|t:|1664062035\n|switch|p2a: Corviknight|Corviknight, F, shiny|100\/100\n|move|p1a: Landorus|Stealth Rock|p2a: Corviknight\n|-sidestart|p2: misplayin|move: Stealth Rock\n|\n|-heal|p1a: Landorus|100\/100 tox|[from] item: Leftovers\n|-damage|p1a: Landorus|88\/100 tox|[from] psn\n|upkeep\n|turn|8\n|\n|t:|1664062037\n|move|p1a: Landorus|U-turn|p2a: Corviknight\n|-resisted|p2a: Corviknight\n|-damage|p2a: Corviknight|97\/100\n|\n|t:|1664062040\n|switch|p1a: Volcanion|Volcanion|95\/100 tox|[from]move: U-turn\n|move|p2a: Corviknight|Defog|p1a: Volcanion\n|-unboost|p1a: Volcanion|evasion|1\n|-sideend|p2: misplayin|Stealth Rock|[from] move: Defog|[of] p2a: Corviknight\n|\n|-heal|p2a: Corviknight|100\/100|[from] item: Leftovers\n|-damage|p1a: Volcanion|89\/100 tox|[from] psn\n|upkeep\n|turn|9\n|inactive|skibsthekid has 210 seconds left.\n|\n|t:|1664062051\n|switch|p2a: Garchomp|Garchomp, M|86\/100\n|move|p1a: Volcanion|Earth Power|p2a: Garchomp\n|-damage|p2a: Garchomp|46\/100\n|\n|-heal|p2a: Garchomp|52\/100|[from] item: Leftovers\n|-damage|p1a: Volcanion|77\/100 tox|[from] psn\n|upkeep\n|turn|10\n|\n|t:|1664062056\n|switch|p1a: Diggersby|Diggersby, M|100\/100\n|move|p2a: Garchomp|Earthquake|p1a: Diggersby\n|-damage|p1a: Diggersby|48\/100\n|\n|-heal|p2a: Garchomp|59\/100|[from] item: Leftovers\n|upkeep\n|turn|11\n|\n|t:|1664062062\n|switch|p1a: Landorus|Landorus-Therian, M|88\/100 tox\n|-ability|p1a: Landorus|Intimidate|boost\n|-unboost|p2a: Garchomp|atk|1\n|move|p2a: Garchomp|Protect||[still]\n|-fail|p2a: Garchomp\n|\n|-heal|p2a: Garchomp|65\/100|[from] item: Leftovers\n|-heal|p1a: Landorus|94\/100 tox|[from] item: Leftovers\n|-damage|p1a: Landorus|88\/100 tox|[from] psn\n|upkeep\n|turn|12\n|\n|t:|1664062068\n|switch|p1a: Diggersby|Diggersby, M|48\/100\n|move|p2a: Garchomp|Stealth Rock|p1a: Diggersby\n|-sidestart|p1: skibsthekid|move: Stealth Rock\n|\n|-heal|p2a: Garchomp|71\/100|[from] item: Leftovers\n|upkeep\n|turn|13\n|c| Rubiaa|bro laid just hit a high note in VC\n|c| Rubiaa|LOL\n|\n|t:|1664062072\n|move|p2a: Garchomp|Protect|p2a: Garchomp\n|-singleturn|p2a: Garchomp|Protect\n|move|p1a: Diggersby|Ice Punch|p2a: Garchomp\n|-activate|p2a: Garchomp|move: Protect\n|\n|-heal|p2a: Garchomp|77\/100|[from] item: Leftovers\n|upkeep\n|turn|14\n|\n|t:|1664062076\n|switch|p2a: Buzzwole|Buzzwole|81\/100\n|move|p1a: Diggersby|Smack Down|p2a: Buzzwole\n|-damage|p2a: Buzzwole|70\/100\n|\n|upkeep\n|turn|15\n|c| UnstoppableUg|LOL\n|inactive|skibsthekid has 240 seconds left.\n|\n|t:|1664062097\n|switch|p1a: Landorus|Landorus-Therian, M|88\/100 tox\n|-damage|p1a: Landorus|76\/100 tox|[from] Stealth Rock\n|-ability|p1a: Landorus|Intimidate|boost\n|-unboost|p2a: Buzzwole|atk|1\n|move|p2a: Buzzwole|Ice Punch|p1a: Landorus\n|-supereffective|p1a: Landorus\n|-damage|p1a: Landorus|15\/100 tox\n|\n|-heal|p1a: Landorus|21\/100 tox|[from] item: Leftovers\n|-damage|p1a: Landorus|15\/100 tox|[from] psn\n|upkeep\n|turn|16\n|\n|t:|1664062103\n|move|p2a: Buzzwole|Ice Punch|p1a: Landorus\n|-supereffective|p1a: Landorus\n|-damage|p1a: Landorus|0 fnt\n|faint|p1a: Landorus\n|-ability|p2a: Buzzwole|Beast Boost|boost\n|-boost|p2a: Buzzwole|def|1\n|\n|upkeep\n|\n|t:|1664062107\n|switch|p1a: Volcanion|Volcanion|77\/100 tox\n|-damage|p1a: Volcanion|52\/100 tox|[from] Stealth Rock\n|turn|17\n|\n|t:|1664062118\n|switch|p2a: Volcanion|Volcanion|100\/100\n|move|p1a: Volcanion|Steam Eruption|p2a: Volcanion\n|-immune|p2a: Volcanion|[from] ability: Water Absorb\n|\n|-damage|p1a: Volcanion|46\/100 tox|[from] psn\n|upkeep\n|turn|18\n|c|\u2606skibsthekid|going out extremely sad :(\n|c| Rubiaa|LOL\n|c| Rubiaa|its aight\n|c| Rubiaa|go get back in nat-dex\n|inactive|misplayin has 270 seconds left.\n|c| UnstoppableUg|Keep playing bro\n|c| UnstoppableUg|Focus\n|c| UnstoppableUg|Calc when needed\n|c| UnstoppableUg|Do what u gotta do\n|c| UnstoppableUg|Play YO game chief\n|inactive|misplayin has 240 seconds left.\n|c| UnstoppableUg|\ud83d\ude4f\ud83d\ude4f\n|\n|t:|1664062189\n|move|p2a: Volcanion|Steam Eruption|p1a: Volcanion\n|-heal|p1a: Volcanion|71\/100 tox|[from] ability: Water Absorb|[of] p2a: Volcanion\n|move|p1a: Volcanion|Steam Eruption|p2a: Volcanion\n|-immune|p2a: Volcanion|[from] ability: Water Absorb\n|\n|-damage|p1a: Volcanion|59\/100 tox|[from] psn\n|upkeep\n|turn|19\n|inactive|misplayin has 240 seconds left.\n|c|\u2606misplayin|lmaoo\n|c| Rubiaa|bro the praying emoji in this game has me dying\n|\n|t:|1664062202\n|move|p1a: Volcanion|Steam Eruption|p2a: Volcanion\n|-immune|p2a: Volcanion|[from] ability: Water Absorb\n|move|p2a: Volcanion|Steam Eruption|p1a: Volcanion\n|-heal|p1a: Volcanion|84\/100 tox|[from] ability: Water Absorb|[of] p2a: Volcanion\n|\n|-damage|p1a: Volcanion|66\/100 tox|[from] psn\n|upkeep\n|turn|20\n|c| UnstoppableUg|Good turn\n|inactive|misplayin has 240 seconds left.\n|c| UnstoppableUg|LOL\n|\n|t:|1664062235\n|switch|p2a: Garchomp|Garchomp, M|77\/100\n|move|p1a: Volcanion|Steam Eruption|p2a: Garchomp\n|-damage|p2a: Garchomp|14\/100\n|\n|-heal|p2a: Garchomp|20\/100|[from] item: Leftovers\n|-damage|p1a: Volcanion|42\/100 tox|[from] psn\n|upkeep\n|turn|21\n|\n|t:|1664062251\n|switch|p1a: Weavile|Weavile, M|100\/100\n|-damage|p1a: Weavile|76\/100|[from] Stealth Rock\n|-ability|p1a: Weavile|Pressure\n|move|p2a: Garchomp|Earthquake|p1a: Weavile\n|-damage|p1a: Weavile|0 fnt\n|faint|p1a: Weavile\n|\n|-heal|p2a: Garchomp|27\/100|[from] item: Leftovers\n|upkeep\n|\n|t:|1664062262\n|switch|p1a: Kartana|Kartana|100\/100\n|-damage|p1a: Kartana|94\/100|[from] Stealth Rock\n|turn|22\n|c| UnstoppableUg|Oof theres Jay name\n|\n|t:|1664062267\n|switch|p2a: Corviknight|Corviknight, F, shiny|100\/100\n|move|p1a: Kartana|Knock Off|p2a: Corviknight\n|-damage|p2a: Corviknight|65\/100\n|-enditem|p2a: Corviknight|Leftovers|[from] move: Knock Off|[of] p1a: Kartana\n|\n|upkeep\n|turn|23\n|c| Rubiaa|knoock oof\n|\n|t:|1664062281\n|move|p1a: Kartana|Knock Off|p2a: Corviknight\n|-crit|p2a: Corviknight\n|-damage|p2a: Corviknight|32\/100\n|move|p2a: Corviknight|U-turn|p1a: Kartana\n|-damage|p1a: Kartana|78\/100\n|\n|t:|1664062295\n|switch|p2a: Tapu Koko|Tapu Koko, shiny|100\/100|[from]move: U-turn\n|-fieldstart|move: Electric Terrain|[from] ability: Electric Surge|[of] p2a: Tapu Koko\n|\n|upkeep\n|turn|24\n|inactive|skibsthekid has 240 seconds left.\n|c|\u2606skibsthekid|can somebody send me the sample team\n|inactive|skibsthekid has 210 seconds left.\n|\n|t:|1664062355\n|move|p1a: Kartana|Knock Off|p2a: Tapu Koko\n|-resisted|p2a: Tapu Koko\n|-damage|p2a: Tapu Koko|71\/100\n|-enditem|p2a: Tapu Koko|Heavy-Duty Boots|[from] move: Knock Off|[of] p1a: Kartana\n|move|p2a: Tapu Koko|Thunderbolt|p1a: Kartana\n|-resisted|p1a: Kartana\n|-damage|p1a: Kartana|5\/100\n|-status|p1a: Kartana|par\n|\n|upkeep\n|turn|25\n|inactive|skibsthekid has 210 seconds left.\n|c|\u2606skibsthekid|i want to fact check lmao\n|\n|t:|1664062371\n|move|p2a: Tapu Koko|Dazzling Gleam|p1a: Kartana\n|-resisted|p1a: Kartana\n|-damage|p1a: Kartana|0 fnt\n|faint|p1a: Kartana\n|\n|upkeep\n|\n|t:|1664062383\n|switch|p1a: Diggersby|Diggersby, M|48\/100\n|-damage|p1a: Diggersby|42\/100|[from] Stealth Rock\n|turn|26\n|\n|t:|1664062389\n|switch|p2a: Buzzwole|Buzzwole|70\/100\n|move|p1a: Diggersby|Earthquake|p2a: Buzzwole\n|-resisted|p2a: Buzzwole\n|-damage|p2a: Buzzwole|54\/100\n|\n|upkeep\n|turn|27\n|\n|t:|1664062391\n|switch|p1a: Zapdos|Zapdos|100\/100\n|move|p2a: Buzzwole|Ice Punch|p1a: Zapdos\n|-supereffective|p1a: Zapdos\n|-damage|p1a: Zapdos|41\/100\n|-status|p2a: Buzzwole|par|[from] ability: Static|[of] p1a: Zapdos\n|\n|-fieldend|move: Electric Terrain\n|upkeep\n|turn|28\n|\n|t:|1664062402\n|switch|p2a: Garchomp|Garchomp, M|27\/100\n|move|p1a: Zapdos|Hurricane|p2a: Garchomp\n|-damage|p2a: Garchomp|0 fnt\n|faint|p2a: Garchomp\n|\n|upkeep\n|\n|t:|1664062407\n|switch|p2a: Tapu Koko|Tapu Koko, shiny|71\/100\n|-fieldstart|move: Electric Terrain|[from] ability: Electric Surge|[of] p2a: Tapu Koko\n|turn|29\n|\n|t:|1664062412\n|switch|p1a: Volcanion|Volcanion|42\/100 tox\n|-damage|p1a: Volcanion|17\/100 tox|[from] Stealth Rock\n|move|p2a: Tapu Koko|Thunderbolt|p1a: Volcanion\n|-supereffective|p1a: Volcanion\n|-damage|p1a: Volcanion|0 fnt\n|faint|p1a: Volcanion\n|\n|upkeep\n|\n|t:|1664062414\n|switch|p1a: Diggersby|Diggersby, M|42\/100\n|-damage|p1a: Diggersby|36\/100|[from] Stealth Rock\n|turn|30\n|\n|t:|1664062416\n|move|p2a: Tapu Koko|Dazzling Gleam|p1a: Diggersby\n|-damage|p1a: Diggersby|12\/100\n|move|p1a: Diggersby|Earthquake|p2a: Tapu Koko\n|-supereffective|p2a: Tapu Koko\n|-damage|p2a: Tapu Koko|0 fnt\n|faint|p2a: Tapu Koko\n|\n|upkeep\n|\n|t:|1664062423\n|switch|p2a: Zapdos|Zapdos-Galar|100\/100\n|turn|31\n|c| UnstoppableUg|AVVV\n|c|\u2606misplayin|oh\n|c|\u2606misplayin|things got spicy\n|c| UnstoppableUg|YOOOOOOO\n|c| Rubiaa|it is\n|\n|t:|1664062438\n|move|p2a: Zapdos|Brave Bird|p1a: Diggersby\n|-damage|p1a: Diggersby|0 fnt\n|faint|p1a: Diggersby\n|-damage|p2a: Zapdos|96\/100|[from] Recoil\n|\n|upkeep\n|c| Rubiaa|zapdos might fuck yo ass up\n|c| UnstoppableUg|THATS BRAAAAAZZZYYYYY\n|\n|t:|1664062440\n|switch|p1a: Zapdos|Zapdos|41\/100\n|turn|32\n|\n|t:|1664062442\n|move|p2a: Zapdos|Brave Bird|p1a: Zapdos\n|-resisted|p1a: Zapdos\n|-damage|p1a: Zapdos|0 fnt\n|faint|p1a: Zapdos\n|-damage|p2a: Zapdos|83\/100|[from] Recoil\n|\n|win|misplayin\n|c| Rubiaa|nvm\n|c|\u2606skibsthekid|aw fuck gg\n|c| Rubiaa|gapdos is broken\n|c| Rubiaa|LOL\n|c|\u2606misplayin|gg\n|c|\u2606skibsthekid|it was a good try\n|c| UnstoppableUg|Nope\n|c| UnstoppableUg|Lmao\n|c| Rubiaa|even then\n|c| UnstoppableUg|Welp here comes Nat Dex\n|c| UnstoppableUg|Lmao\n|j| laidbackk\n|c| Rubiaa|LMFAOO\n|c|\u2606skibsthekid|are you banded on gapdos?\n|c| Rubiaa|yea probs\n|c| Rubiaa|banded jolly\n|c| Rubiaa|i cant see it killing otherwise\n|c|\u2606misplayin|yh\n|c|\u2606misplayin|banded only real set\n|c|\u2606skibsthekid|ah yeah i was super dead then\n|c|\u2606skibsthekid|winning speed tie was my chance\n|c|\u2606misplayin|scary of ass game\n|c|\u2606skibsthekid|ye we're playing nat dex g3 haha\n|c|\u2606skibsthekid|dude whenever we play we get great sets\n|c|\u2606skibsthekid|i love playing v you\n|c|\u2606misplayin|u2 homie\n|c|\u2606skibsthekid|did you find\n|c|\u2606skibsthekid|the sample team btw\n|c|\u2606skibsthekid|like actually\n|c|\u2606skibsthekid|theres no way she just sent me a sample team right\n|c|\u2606skibsthekid|surely\n|c| Rubiaa|if yall ni66as dont get to g3\n|c| Rubiaa|LOL\n|c|\u2606misplayin|Nah lmao\n|c|\u2606skibsthekid|ok ok hahahaha\n|l| UnstoppableUg\n|l|\u2606skibsthekid\n|l| Rubiaa\n","uploadtime":1664062749,"views":32,"p1id":"skibsthekid","p2id":"misplayin","formatid":"gen8ou","rating":0,"private":0,"password":null}