{"id":"gen8ou-1699709078","p1":"Huskothy","p2":"cump4","format":"gen8ou","log":"|j|\u2606Huskothy\n|j|\u2606cump4\n|t:|1667260210\n|gametype|singles\n|player|p1|Huskothy|lucas|1725\n|player|p2|cump4|schoolkid-gen4|1657\n|teamsize|p1|6\n|teamsize|p2|6\n|gen|8\n|tier|[Gen 8] OU\n|rated|\n|rule|Sleep Clause Mod: Limit one foe put to sleep\n|rule|Species Clause: Limit one of each Pok\u00e9mon\n|rule|OHKO Clause: OHKO moves are banned\n|rule|Evasion Items Clause: Evasion items are banned\n|rule|Evasion Moves Clause: Evasion moves are banned\n|rule|Endless Battle Clause: Forcing endless battles is banned\n|rule|HP Percentage Mod: HP is shown in percentages\n|rule|Dynamax Clause: You cannot dynamax\n|clearpoke\n|poke|p1|Luxray, F|\n|poke|p1|Blacephalon|\n|poke|p1|Rillaboom, F|\n|poke|p1|Urshifu-*, F|\n|poke|p1|Blissey, F|\n|poke|p1|Landorus-Therian, M|\n|poke|p2|Clefable, F|\n|poke|p2|Skarmory, F|\n|poke|p2|Toxapex, F|\n|poke|p2|Weavile, M|\n|poke|p2|Reuniclus, M|\n|poke|p2|Zeraora|\n|teampreview\n|\n|t:|1667260225\n|start\n|switch|p1a: Landorus|Landorus-Therian, M|100\/100\n|switch|p2a: Toxapex|Toxapex, F, shiny|100\/100\n|-ability|p1a: Landorus|Intimidate|boost\n|-unboost|p2a: Toxapex|atk|1\n|turn|1\n|\n|t:|1667260230\n|move|p1a: Landorus|Knock Off|p2a: Toxapex\n|-damage|p2a: Toxapex|81\/100\n|-enditem|p2a: Toxapex|Shed Shell|[from] move: Knock Off|[of] p1a: Landorus\n|move|p2a: Toxapex|Knock Off|p1a: Landorus\n|-damage|p1a: Landorus|93\/100\n|-enditem|p1a: Landorus|Leftovers|[from] move: Knock Off|[of] p2a: Toxapex\n|\n|upkeep\n|turn|2\n|\n|t:|1667260234\n|move|p1a: Landorus|Earth Power|p2a: Toxapex\n|-supereffective|p2a: Toxapex\n|-damage|p2a: Toxapex|30\/100\n|move|p2a: Toxapex|Scald|p1a: Landorus\n|-supereffective|p1a: Landorus\n|-damage|p1a: Landorus|61\/100\n|\n|upkeep\n|turn|3\n|j| Kwaga\n|\n|t:|1667260239\n|switch|p2a: Skarmory|Skarmory, F, shiny|100\/100\n|move|p1a: Landorus|Knock Off|p2a: Skarmory\n|-damage|p2a: Skarmory|86\/100\n|-enditem|p2a: Skarmory|Leftovers|[from] move: Knock Off|[of] p1a: Landorus\n|\n|upkeep\n|turn|4\n|\n|t:|1667260243\n|move|p1a: Landorus|U-turn|p2a: Skarmory\n|-resisted|p2a: Skarmory\n|-damage|p2a: Skarmory|83\/100\n|\n|t:|1667260248\n|switch|p1a: Blissey|Blissey, F|100\/100|[from]move: U-turn\n|move|p2a: Skarmory|Spikes|p1a: Blissey\n|-sidestart|p1: Huskothy|Spikes\n|\n|upkeep\n|turn|5\n|\n|t:|1667260250\n|move|p2a: Skarmory|Spikes|p1a: Blissey\n|-sidestart|p1: Huskothy|Spikes\n|move|p1a: Blissey|Stealth Rock|p2a: Skarmory\n|-sidestart|p2: cump4|move: Stealth Rock\n|\n|upkeep\n|turn|6\n|\n|t:|1667260257\n|switch|p1a: Blacephalon|Blacephalon|100\/100\n|-damage|p1a: Blacephalon|84\/100|[from] Spikes\n|move|p2a: Skarmory|Spikes|p1a: Blacephalon\n|-sidestart|p1: Huskothy|Spikes\n|\n|upkeep\n|turn|7\n|\n|t:|1667260267\n|switch|p2a: Toxapex|Toxapex, F, shiny|63\/100\n|-damage|p2a: Toxapex|51\/100|[from] Stealth Rock\n|move|p1a: Blacephalon|Shadow Ball|p2a: Toxapex\n|-damage|p2a: Toxapex|5\/100\n|-unboost|p2a: Toxapex|spd|1\n|\n|upkeep\n|turn|8\n|\n|t:|1667260270\n|switch|p2a: Weavile|Weavile, M|100\/100\n|-ability|p2a: Weavile|Pressure\n|move|p1a: Blacephalon|Shadow Ball|p2a: Weavile\n|-resisted|p2a: Weavile\n|-damage|p2a: Weavile|50\/100\n|-unboost|p2a: Weavile|spd|1\n|\n|upkeep\n|turn|9\n|\n|t:|1667260279\n|switch|p1a: Landorus|Landorus-Therian, M|61\/100\n|-ability|p1a: Landorus|Intimidate|boost\n|-unboost|p2a: Weavile|atk|1\n|move|p2a: Weavile|Knock Off|p1a: Landorus\n|-damage|p1a: Landorus|42\/100\n|\n|upkeep\n|turn|10\n|\n|t:|1667260284\n|switch|p1a: Urshifu|Urshifu-Rapid-Strike, F|100\/100\n|-damage|p1a: Urshifu|76\/100|[from] Spikes\n|move|p2a: Weavile|Icicle Crash|p1a: Urshifu\n|-resisted|p1a: Urshifu\n|-damage|p1a: Urshifu|60\/100\n|\n|upkeep\n|turn|11\n|\n|t:|1667260287\n|switch|p2a: Clefable|Clefable, F|100\/100\n|move|p1a: Urshifu|U-turn|p2a: Clefable\n|-resisted|p2a: Clefable\n|-damage|p2a: Clefable|90\/100\n|-damage|p1a: Urshifu|44\/100|[from] item: Rocky Helmet|[of] p2a: Clefable\n|\n|t:|1667260295\n|switch|p1a: Luxray|Luxray, F|100\/100|[from]move: U-turn\n|-damage|p1a: Luxray|75\/100|[from] Spikes\n|\n|-status|p1a: Luxray|brn|[from] item: Flame Orb\n|upkeep\n|turn|12\n|\n|t:|1667260299\n|switch|p2a: Zeraora|Zeraora|100\/100\n|move|p1a: Luxray|Facade|p2a: Zeraora\n|-damage|p2a: Zeraora|0 fnt\n|faint|p2a: Zeraora\n|\n|-damage|p1a: Luxray|69\/100 brn|[from] brn\n|upkeep\n|\n|t:|1667260306\n|switch|p2a: Weavile|Weavile, M|50\/100\n|-ability|p2a: Weavile|Pressure\n|turn|13\n|\n|t:|1667260312\n|move|p2a: Weavile|Icicle Crash|p1a: Luxray\n|-damage|p1a: Luxray|15\/100 brn\n|move|p1a: Luxray|Facade|p2a: Weavile\n|-damage|p2a: Weavile|0 fnt\n|faint|p2a: Weavile\n|\n|-damage|p1a: Luxray|8\/100 brn|[from] brn\n|upkeep\n|\n|t:|1667260319\n|switch|p2a: Skarmory|Skarmory, F, shiny|83\/100\n|-damage|p2a: Skarmory|71\/100|[from] Stealth Rock\n|turn|14\n|\n|t:|1667260321\n|move|p1a: Luxray|Wild Charge|p2a: Skarmory\n|-supereffective|p2a: Skarmory\n|-damage|p2a: Skarmory|0 fnt\n|faint|p2a: Skarmory\n|-damage|p1a: Luxray|0 fnt|[from] Recoil\n|faint|p1a: Luxray\n|\n|upkeep\n|\n|t:|1667260337\n|switch|p1a: Rillaboom|Rillaboom, F|100\/100\n|switch|p2a: Clefable|Clefable, F|90\/100\n|-damage|p1a: Rillaboom|76\/100|[from] Spikes\n|-fieldstart|move: Grassy Terrain|[from] ability: Grassy Surge|[of] p1a: Rillaboom\n|turn|15\n|\n|t:|1667260341\n|move|p1a: Rillaboom|Swords Dance|p1a: Rillaboom\n|-boost|p1a: Rillaboom|atk|2\n|move|p2a: Clefable|Thunder Wave|p1a: Rillaboom\n|-status|p1a: Rillaboom|par\n|\n|-heal|p2a: Clefable|96\/100|[from] Grassy Terrain\n|-heal|p1a: Rillaboom|82\/100 par|[from] Grassy Terrain\n|upkeep\n|turn|16\n|\n|t:|1667260344\n|switch|p2a: Reuniclus|Reuniclus, M, shiny|100\/100\n|move|p1a: Rillaboom|Grassy Glide|p2a: Reuniclus\n|-damage|p2a: Reuniclus|32\/100\n|\n|-heal|p1a: Rillaboom|88\/100 par|[from] Grassy Terrain\n|-heal|p2a: Reuniclus|38\/100|[from] Grassy Terrain\n|-heal|p2a: Reuniclus|45\/100|[from] item: Leftovers\n|upkeep\n|turn|17\n|l| Kwaga\n|\n|t:|1667260347\n|move|p1a: Rillaboom|Grassy Glide|p2a: Reuniclus\n|-damage|p2a: Reuniclus|0 fnt\n|faint|p2a: Reuniclus\n|\n|-heal|p1a: Rillaboom|94\/100 par|[from] Grassy Terrain\n|upkeep\n|-message|cump4 forfeited.\n|\n|win|Huskothy\n|raw|Huskothy's rating: 1725 &rarr; <strong>1741<\/strong><br \/>(+16 for winning)\n|raw|cump4's rating: 1657 &rarr; <strong>1641<\/strong><br \/>(-16 for losing)\n||Ladder isn't responding, score probably updated but might not have (Request timeout).\n","uploadtime":1667260356,"views":6,"p1id":"huskothy","p2id":"cump4","formatid":"gen8ou","rating":1641,"private":0,"password":null}