{"id":"gen8ou-1692107175","p1":"Trogba Trogba","p2":"Schizo Shroomz","format":"gen8ou","log":"|html|<div class=\"broadcast-blue\"><strong>[Gen 8] OU is currently suspecting Melmetal! For information on how to participate check out the <a href=\"https:\/\/www.smogon.com\/forums\/threads\/np-ss-ou-suspect-process-round-12-monster-mash.3709234\/\">suspect thread<\/a>.<\/strong><\/div>\n|j|\u2606Trogba Trogba\n|j|\u2606Schizo Shroomz\n|inactive|Battle timer is ON: inactive players will automatically lose when time's up.\n|t:|1666452587\n|gametype|singles\n|player|p1|Trogba Trogba|265|\n|player|p2|Schizo Shroomz|beauty-gen2|\n|teamsize|p1|6\n|teamsize|p2|6\n|gen|8\n|tier|[Gen 8] OU\n|rated|Tournament battle\n|rule|Sleep Clause Mod: Limit one foe put to sleep\n|rule|Species Clause: Limit one of each Pok\u00e9mon\n|rule|OHKO Clause: OHKO moves are banned\n|rule|Evasion Items Clause: Evasion items are banned\n|rule|Evasion Moves Clause: Evasion moves are banned\n|rule|Endless Battle Clause: Forcing endless battles is banned\n|rule|HP Percentage Mod: HP is shown in percentages\n|rule|Dynamax Clause: You cannot dynamax\n|clearpoke\n|poke|p1|Dragapult, M|\n|poke|p1|Landorus-Therian, M|\n|poke|p1|Weavile, F|\n|poke|p1|Ferrothorn, M|\n|poke|p1|Blaziken, F|\n|poke|p1|Tapu Lele|\n|poke|p2|Garchomp, M|\n|poke|p2|Buzzwole|\n|poke|p2|Magnezone|\n|poke|p2|Dragonite, M|\n|poke|p2|Slowking, F|\n|poke|p2|Excadrill, M|\n|teampreview\n|j| svenno\n|j|@Mimikyu Stardust\n|j|@Sww-Suwa\n|c|\u2606Trogba Trogba|glhf\n|j| Reeynee\n|j| sufy512\n|j| blooclipsesucks\n|j| Down$pook\n|c|\u2606Schizo Shroomz|U2\n|j| Faceblue\n|j| 6yrOldBongWater\n|l| blooclipsesucks\n|j| SlothsWrath\n|j| GoatNoir\n|\n|t:|1666452610\n|start\n|switch|p1a: Dragapult|Dragapult, M|100\/100\n|switch|p2a: Excadrill|Excadrill, M|100\/100\n|-ability|p2a: Excadrill|Mold Breaker\n|turn|1\n|j| SOSSWORLD\n|c| GoatNoir|Lele kinda looks scary\n|inactive|Trogba Trogba has 120 seconds left.\n|j| X-Wing Fighter\n|\n|t:|1666452652\n|move|p2a: Excadrill|Earthquake|p1a: Dragapult\n|-damage|p1a: Dragapult|27\/100\n|move|p1a: Dragapult|Fire Blast|p2a: Excadrill\n|-supereffective|p2a: Excadrill\n|-damage|p2a: Excadrill|0 fnt\n|faint|p2a: Excadrill\n|\n|upkeep\n|c| Faceblue|No u\n|\n|t:|1666452658\n|switch|p2a: DRACARYS|Garchomp, M|100\/100\n|turn|2\n|l| X-Wing Fighter\n|inactive|Trogba Trogba has 120 seconds left.\n|\n|t:|1666452668\n|switch|p1a: Landorus|Landorus-Therian, M|100\/100\n|-ability|p1a: Landorus|Intimidate|boost\n|-unboost|p2a: DRACARYS|atk|1\n|move|p2a: DRACARYS|Stealth Rock|p1a: Landorus\n|-sidestart|p1: Trogba Trogba|move: Stealth Rock\n|\n|upkeep\n|turn|3\n|\n|t:|1666452675\n|switch|p2a: JON SNOW|Slowking, F|100\/100\n|move|p1a: Landorus|Defog|p2a: JON SNOW\n|-unboost|p2a: JON SNOW|evasion|1\n|-sideend|p1: Trogba Trogba|Stealth Rock|[from] move: Defog|[of] p1a: Landorus\n|\n|upkeep\n|turn|4\n|\n|t:|1666452680\n|move|p1a: Landorus|Stealth Rock|p2a: JON SNOW\n|-sidestart|p2: Schizo Shroomz|move: Stealth Rock\n|move|p2a: JON SNOW|Scald|p1a: Landorus\n|-supereffective|p1a: Landorus\n|-damage|p1a: Landorus|60\/100\n|-enditem|p1a: Landorus|Eject Button\n|\n|t:|1666452684\n|switch|p1a: Weavile|Weavile, F|100\/100\n|-ability|p1a: Weavile|Pressure\n|\n|upkeep\n|turn|5\n|\n|t:|1666452686\n|switch|p2a: MOUNTAIN|Buzzwole|100\/100\n|-damage|p2a: MOUNTAIN|88\/100|[from] Stealth Rock\n|move|p1a: Weavile|Knock Off|p2a: MOUNTAIN\n|-resisted|p2a: MOUNTAIN\n|-damage|p2a: MOUNTAIN|67\/100\n|-damage|p1a: Weavile|84\/100|[from] item: Rocky Helmet|[of] p2a: MOUNTAIN\n|-enditem|p2a: MOUNTAIN|Rocky Helmet|[from] move: Knock Off|[of] p1a: Weavile\n|\n|upkeep\n|turn|6\n|\n|t:|1666452705\n|switch|p1a: Blaziken|Blaziken, F|100\/100\n|move|p2a: MOUNTAIN|Roost|p2a: MOUNTAIN\n|-heal|p2a: MOUNTAIN|100\/100\n|-singleturn|p2a: MOUNTAIN|move: Roost\n|\n|upkeep\n|turn|7\n|c| SOSSWORLD|Wat a play\n|\n|t:|1666452713\n|switch|p1a: Landorus|Landorus-Therian, M|60\/100\n|-ability|p1a: Landorus|Intimidate|boost\n|-unboost|p2a: MOUNTAIN|atk|1\n|switch|p2a: VISERYS|Dragonite, M|100\/100\n|\n|upkeep\n|turn|8\n|\n|t:|1666452736\n|switch|p1a: Ferrothorn|Ferrothorn, M|100\/100\n|move|p2a: VISERYS|Dual Wingbeat|p1a: Ferrothorn|[miss]\n|-miss|p2a: VISERYS|p1a: Ferrothorn\n|\n|upkeep\n|turn|9\n|c|\u2606Trogba Trogba|ffs\n|l| SOSSWORLD\n|\n|t:|1666452744\n|switch|p2a: Magnezone|Magnezone|100\/100\n|-damage|p2a: Magnezone|94\/100|[from] Stealth Rock\n|move|p1a: Ferrothorn|Leech Seed|p2a: Magnezone\n|-start|p2a: Magnezone|move: Leech Seed\n|\n|-heal|p2a: Magnezone|100\/100|[from] item: Leftovers\n|-damage|p2a: Magnezone|88\/100|[from] Leech Seed|[of] p1a: Ferrothorn\n|upkeep\n|turn|10\n|\n|t:|1666452752\n|move|p2a: Magnezone|Iron Defense|p2a: Magnezone\n|-boost|p2a: Magnezone|def|2\n|move|p1a: Ferrothorn|Knock Off|p2a: Magnezone\n|-damage|p2a: Magnezone|80\/100\n|-enditem|p2a: Magnezone|Leftovers|[from] move: Knock Off|[of] p1a: Ferrothorn\n|\n|-damage|p2a: Magnezone|67\/100|[from] Leech Seed|[of] p1a: Ferrothorn\n|upkeep\n|turn|11\n|\n|t:|1666452754\n|move|p2a: Magnezone|Iron Defense|p2a: Magnezone\n|-boost|p2a: Magnezone|def|2\n|move|p1a: Ferrothorn|Spikes|p2a: Magnezone\n|-sidestart|p2: Schizo Shroomz|Spikes\n|\n|-damage|p2a: Magnezone|55\/100|[from] Leech Seed|[of] p1a: Ferrothorn\n|upkeep\n|turn|12\n|\n|t:|1666452756\n|move|p2a: Magnezone|Body Press|p1a: Ferrothorn\n|-supereffective|p1a: Ferrothorn\n|-damage|p1a: Ferrothorn|11\/100\n|-damage|p2a: Magnezone|43\/100|[from] ability: Iron Barbs|[of] p1a: Ferrothorn\n|-damage|p2a: Magnezone|26\/100|[from] item: Rocky Helmet|[of] p1a: Ferrothorn\n|move|p1a: Ferrothorn|Spikes|p2a: Magnezone\n|-sidestart|p2: Schizo Shroomz|Spikes\n|\n|-damage|p2a: Magnezone|14\/100|[from] Leech Seed|[of] p1a: Ferrothorn\n|-heal|p1a: Ferrothorn|22\/100|[silent]\n|upkeep\n|turn|13\n|\n|t:|1666452764\n|move|p2a: Magnezone|Body Press|p1a: Ferrothorn\n|-supereffective|p1a: Ferrothorn\n|-damage|p1a: Ferrothorn|0 fnt\n|-damage|p2a: Magnezone|1\/100|[from] ability: Iron Barbs|[of] p1a: Ferrothorn\n|-damage|p2a: Magnezone|0 fnt|[from] item: Rocky Helmet|[of] p1a: Ferrothorn\n|faint|p1a: Ferrothorn\n|faint|p2a: Magnezone\n|\n|upkeep\n|j| SOSSWORLD\n|\n|t:|1666452775\n|switch|p2a: MOUNTAIN|Buzzwole|100\/100\n|switch|p1a: Weavile|Weavile, F|84\/100\n|-ability|p1a: Weavile|Pressure\n|-damage|p2a: MOUNTAIN|88\/100|[from] Stealth Rock\n|-damage|p2a: MOUNTAIN|71\/100|[from] Spikes\n|turn|14\n|j| Paltham\n|\n|t:|1666452785\n|switch|p1a: Dragapult|Dragapult, M|27\/100\n|move|p2a: MOUNTAIN|Leech Life|p1a: Dragapult\n|-resisted|p1a: Dragapult\n|-damage|p1a: Dragapult|0 fnt\n|-heal|p2a: MOUNTAIN|82\/100|[from] drain|[of] p1a: Dragapult\n|faint|p1a: Dragapult\n|-ability|p2a: MOUNTAIN|Beast Boost|boost\n|-boost|p2a: MOUNTAIN|def|1\n|\n|upkeep\n|\n|t:|1666452788\n|switch|p1a: Tapu Lele|Tapu Lele|100\/100\n|-fieldstart|move: Psychic Terrain|[from] ability: Psychic Surge|[of] p1a: Tapu Lele\n|turn|15\n|\n|t:|1666452793\n|switch|p2a: JON SNOW|Slowking, F|100\/100\n|move|p1a: Tapu Lele|Moonblast|p2a: JON SNOW\n|-damage|p2a: JON SNOW|72\/100\n|\n|upkeep\n|turn|16\n|c| 6yrOldBongWater|we wuz playin tag\n|\n|t:|1666452799\n|move|p1a: Tapu Lele|Moonblast|p2a: JON SNOW\n|-damage|p2a: JON SNOW|41\/100\n|move|p2a: JON SNOW|Teleport|p2a: JON SNOW\n|\n|t:|1666452805\n|switch|p2a: VISERYS|Dragonite, M|100\/100|[from]move: Teleport\n|\n|upkeep\n|turn|17\n|\n|t:|1666452825\n|switch|p2a: JON SNOW|Slowking, F|74\/100\n|move|p1a: Tapu Lele|Moonblast|p2a: JON SNOW\n|-damage|p2a: JON SNOW|46\/100\n|\n|upkeep\n|turn|18\n|\n|t:|1666452831\n|switch|p1a: Weavile|Weavile, F|84\/100\n|-ability|p1a: Weavile|Pressure\n|move|p2a: JON SNOW|Slack Off|p2a: JON SNOW\n|-heal|p2a: JON SNOW|96\/100\n|\n|upkeep\n|turn|19\n|\n|t:|1666452838\n|move|p1a: Weavile|Triple Axel|p2a: JON SNOW|[miss]\n|-miss|p1a: Weavile|p2a: JON SNOW\n|move|p2a: JON SNOW|Scald|p1a: Weavile\n|-damage|p1a: Weavile|43\/100\n|\n|-fieldend|move: Psychic Terrain\n|upkeep\n|turn|20\n|c| GoatNoir|lele is insane now\n|c|\u2606Trogba Trogba|that mattered\n|c| GoatNoir|there is really nothing against it\n|inactive|Trogba Trogba has 120 seconds left.\n|c|\u2606Trogba Trogba|except king with boots\n|c|\u2606Schizo Shroomz|did melm get banned\n|l| SOSSWORLD\n|c|\u2606Trogba Trogba|still getting tested\n|j| SOSSWORLD\n|c|\u2606Trogba Trogba|I'm voting no\n|inactive|Trogba Trogba has 90 seconds left.\n|c|\u2606Trogba Trogba|I think most others are too\n|\n|t:|1666452909\n|switch|p1a: Tapu Lele|Tapu Lele|100\/100\n|-fieldstart|move: Psychic Terrain|[from] ability: Psychic Surge|[of] p1a: Tapu Lele\n|switch|p2a: MOUNTAIN|Buzzwole|82\/100\n|-damage|p2a: MOUNTAIN|69\/100|[from] Stealth Rock\n|-damage|p2a: MOUNTAIN|53\/100|[from] Spikes\n|\n|upkeep\n|turn|21\n|c| SOSSWORLD|I\u2019m voting yes\n|\n|t:|1666452914\n|switch|p2a: JON SNOW|Slowking, F|100\/100\n|move|p1a: Tapu Lele|Future Sight|p2a: JON SNOW\n|-start|p1a: Tapu Lele|move: Future Sight\n|\n|upkeep\n|turn|22\n|inactive|Trogba Trogba has 90 seconds left.\n|c| Paltham|why sus melm in the first place\n|c| SOSSWORLD|So are my 50 alt accounts\n|\n|t:|1666452928\n|switch|p1a: Landorus|Landorus-Therian, M|60\/100\n|-ability|p1a: Landorus|Intimidate|boost\n|-unboost|p2a: JON SNOW|atk|1\n|move|p2a: JON SNOW|Scald|p1a: Landorus\n|-supereffective|p1a: Landorus\n|-damage|p1a: Landorus|15\/100\n|-status|p1a: Landorus|brn\n|\n|-damage|p1a: Landorus|9\/100 brn|[from] brn\n|upkeep\n|turn|23\n|inactive|Trogba Trogba has 90 seconds left.\n|c| sufy512|SOSSWORLD have u even got reqs\n|c| 6yrOldBongWater|ouuu\n|c| SOSSWORLD|Maybe\n|c| Paltham|surprised they didnt suspect lando-t\n|\n|t:|1666452948\n|switch|p1a: Tapu Lele|Tapu Lele|100\/100\n|move|p2a: JON SNOW|Scald|p1a: Tapu Lele\n|-damage|p1a: Tapu Lele|70\/100\n|\n|-end|p2a: JON SNOW|move: Future Sight\n|-resisted|p2a: JON SNOW\n|-damage|p2a: JON SNOW|74\/100\n|upkeep\n|turn|24\n|c| sufy512|i 'll take that as a no, lmao.\n|\n|t:|1666452963\n|move|p1a: Tapu Lele|Future Sight|p2a: JON SNOW\n|-start|p1a: Tapu Lele|move: Future Sight\n|move|p2a: JON SNOW|Teleport|p2a: JON SNOW\n|\n|t:|1666452965\n|switch|p2a: DRACARYS|Garchomp, M|100\/100|[from]move: Teleport\n|-damage|p2a: DRACARYS|94\/100|[from] Stealth Rock\n|-damage|p2a: DRACARYS|78\/100|[from] Spikes\n|\n|-fieldend|move: Psychic Terrain\n|upkeep\n|turn|25\n|c| sufy512|Paltham why would lando ever be suspected\n|\n|t:|1666452970\n|switch|p1a: Landorus|Landorus-Therian, M|9\/100 brn\n|-ability|p1a: Landorus|Intimidate|boost\n|-unboost|p2a: DRACARYS|atk|1\n|move|p2a: DRACARYS|Stealth Rock|p1a: Landorus\n|-sidestart|p1: Trogba Trogba|move: Stealth Rock\n|\n|-damage|p1a: Landorus|3\/100 brn|[from] brn\n|upkeep\n|turn|26\n|\n|t:|1666452981\n|switch|p2a: JON SNOW|Slowking, F|100\/100\n|move|p1a: Landorus|Defog|p2a: JON SNOW\n|-unboost|p2a: JON SNOW|evasion|1\n|-sideend|p2: Schizo Shroomz|Spikes|[from] move: Defog|[of] p1a: Landorus\n|-sideend|p2: Schizo Shroomz|Stealth Rock|[from] move: Defog|[of] p1a: Landorus\n|-sideend|p1: Trogba Trogba|Stealth Rock|[from] move: Defog|[of] p1a: Landorus\n|\n|-end|p2a: JON SNOW|move: Future Sight\n|-resisted|p2a: JON SNOW\n|-damage|p2a: JON SNOW|80\/100\n|-damage|p1a: Landorus|0 fnt|[from] brn\n|faint|p1a: Landorus\n|upkeep\n|\n|t:|1666452985\n|switch|p1a: Weavile|Weavile, F|43\/100\n|-ability|p1a: Weavile|Pressure\n|turn|27\n|\n|t:|1666452992\n|switch|p2a: MOUNTAIN|Buzzwole|53\/100\n|move|p1a: Weavile|Triple Axel|p2a: MOUNTAIN\n|-damage|p2a: MOUNTAIN|43\/100\n|-damage|p2a: MOUNTAIN|24\/100\n|-hitcount|p2a: MOUNTAIN|2\n|\n|upkeep\n|turn|28\n|c| Faceblue|Im voting ban and i have reqs \ud83d\ude0f\n|c| Paltham|just seems like something they would do lmao\n|c|\u2606Trogba Trogba|cmon dude\n|\n|t:|1666453006\n|switch|p2a: JON SNOW|Slowking, F|100\/100\n|move|p1a: Weavile|Triple Axel|p2a: JON SNOW\n|-resisted|p2a: JON SNOW\n|-crit|p2a: JON SNOW\n|-damage|p2a: JON SNOW|87\/100\n|-resisted|p2a: JON SNOW\n|-damage|p2a: JON SNOW|72\/100\n|-resisted|p2a: JON SNOW\n|-damage|p2a: JON SNOW|46\/100\n|-hitcount|p2a: JON SNOW|3\n|\n|upkeep\n|turn|29\n|c| 6yrOldBongWater|lucky\n|c| SOSSWORLD|Maybe use a move that hits\n|\n|t:|1666453023\n|switch|p2a: MOUNTAIN|Buzzwole|24\/100\n|move|p1a: Weavile|Triple Axel|p2a: MOUNTAIN|[miss]\n|-miss|p1a: Weavile|p2a: MOUNTAIN\n|\n|upkeep\n|turn|30\n|c| SOSSWORLD|3 times next time\n|\n|t:|1666453027\n|move|p1a: Weavile|Triple Axel|p2a: MOUNTAIN\n|-damage|p2a: MOUNTAIN|15\/100\n|-damage|p2a: MOUNTAIN|0 fnt\n|faint|p2a: MOUNTAIN\n|-hitcount|p2: MOUNTAIN|2\n|\n|upkeep\n|c|\u2606Trogba Trogba|ahahaha\n|\n|t:|1666453029\n|switch|p2a: JON SNOW|Slowking, F|79\/100\n|turn|31\n|\n|t:|1666453040\n|switch|p1a: Blaziken|Blaziken, F|100\/100\n|move|p2a: JON SNOW|Scald|p1a: Blaziken\n|-supereffective|p1a: Blaziken\n|-damage|p1a: Blaziken|24\/100\n|\n|-heal|p1a: Blaziken|30\/100|[from] item: Leftovers\n|upkeep\n|turn|32\n|c| Paltham|worlds shortest ou match\n|\n|t:|1666453051\n|switch|p2a: VISERYS|Dragonite, M|100\/100\n|move|p1a: Blaziken|Flare Blitz|p2a: VISERYS\n|-resisted|p2a: VISERYS\n|-damage|p2a: VISERYS|88\/100\n|-damage|p1a: Blaziken|25\/100|[from] Recoil\n|\n|-heal|p1a: Blaziken|31\/100|[from] item: Leftovers\n|-ability|p1a: Blaziken|Speed Boost|boost\n|-boost|p1a: Blaziken|spe|1\n|upkeep\n|turn|33\n|c| GoatNoir|at least now\n|c| GoatNoir|its over\n|inactive|Trogba Trogba has 120 seconds left.\n|\n|t:|1666453081\n|move|p1a: Blaziken|Swords Dance|p1a: Blaziken\n|-boost|p1a: Blaziken|atk|2\n|move|p2a: VISERYS|Dragon Dance|p2a: VISERYS\n|-boost|p2a: VISERYS|atk|1\n|-boost|p2a: VISERYS|spe|1\n|\n|-heal|p1a: Blaziken|37\/100|[from] item: Leftovers\n|-ability|p1a: Blaziken|Speed Boost|boost\n|-boost|p1a: Blaziken|spe|1\n|upkeep\n|turn|34\n|\n|t:|1666453084\n|move|p1a: Blaziken|Close Combat|p2a: VISERYS\n|-resisted|p2a: VISERYS\n|-damage|p2a: VISERYS|35\/100\n|-unboost|p1a: Blaziken|def|1\n|-unboost|p1a: Blaziken|spd|1\n|move|p2a: VISERYS|Roost|p2a: VISERYS\n|-heal|p2a: VISERYS|85\/100\n|-singleturn|p2a: VISERYS|move: Roost\n|\n|-heal|p1a: Blaziken|43\/100|[from] item: Leftovers\n|-ability|p1a: Blaziken|Speed Boost|boost\n|-boost|p1a: Blaziken|spe|1\n|upkeep\n|turn|35\n|c| 6yrOldBongWater|is a good one\n|\n|t:|1666453090\n|move|p1a: Blaziken|Close Combat|p2a: VISERYS\n|-resisted|p2a: VISERYS\n|-damage|p2a: VISERYS|34\/100\n|-unboost|p1a: Blaziken|def|1\n|-unboost|p1a: Blaziken|spd|1\n|move|p2a: VISERYS|Roost|p2a: VISERYS\n|-heal|p2a: VISERYS|84\/100\n|-singleturn|p2a: VISERYS|move: Roost\n|\n|-heal|p1a: Blaziken|49\/100|[from] item: Leftovers\n|-ability|p1a: Blaziken|Speed Boost|boost\n|-boost|p1a: Blaziken|spe|1\n|upkeep\n|turn|36\n|\n|t:|1666453099\n|move|p1a: Blaziken|Close Combat|p2a: VISERYS\n|-resisted|p2a: VISERYS\n|-damage|p2a: VISERYS|29\/100\n|-unboost|p1a: Blaziken|def|1\n|-unboost|p1a: Blaziken|spd|1\n|move|p2a: VISERYS|Dual Wingbeat|p1a: Blaziken\n|-supereffective|p1a: Blaziken\n|-damage|p1a: Blaziken|0 fnt\n|faint|p1a: Blaziken\n|-hitcount|p1: Blaziken|1\n|\n|upkeep\n|\n|t:|1666453108\n|switch|p1a: Tapu Lele|Tapu Lele|70\/100\n|-fieldstart|move: Psychic Terrain|[from] ability: Psychic Surge|[of] p1a: Tapu Lele\n|turn|37\n|c| GoatNoir|if its scarf lele its over\n|\n|t:|1666453118\n|switch|p2a: JON SNOW|Slowking, F|100\/100\n|move|p1a: Tapu Lele|Moonblast|p2a: JON SNOW\n|-damage|p2a: JON SNOW|71\/100\n|\n|upkeep\n|turn|38\n|c| sufy512|no\n|\n|t:|1666453130\n|move|p1a: Tapu Lele|Moonblast|p2a: JON SNOW\n|-damage|p2a: JON SNOW|39\/100\n|move|p2a: JON SNOW|Slack Off|p2a: JON SNOW\n|-heal|p2a: JON SNOW|89\/100\n|\n|upkeep\n|turn|39\n|c| GoatNoir|yes\n|\n|t:|1666453138\n|move|p1a: Tapu Lele|Moonblast|p2a: JON SNOW\n|-damage|p2a: JON SNOW|56\/100\n|-unboost|p2a: JON SNOW|spa|1\n|move|p2a: JON SNOW|Slack Off|p2a: JON SNOW\n|-heal|p2a: JON SNOW|100\/100\n|\n|upkeep\n|turn|40\n|c| sufy512|no lol the slowking walls\n|c| 6yrOldBongWater|slipped\n|c| Paltham|THE KING\n|\n|t:|1666453154\n|move|p1a: Tapu Lele|Moonblast|p2a: JON SNOW\n|-damage|p2a: JON SNOW|72\/100\n|move|p2a: JON SNOW|Teleport|p2a: JON SNOW\n|c| Paltham|the king has arrived\n|c| SOSSWORLD|Erm\n|\n|t:|1666453162\n|switch|p2a: DRACARYS|Garchomp, M|78\/100|[from]move: Teleport\n|\n|upkeep\n|turn|41\n|j| fork you phil\n|c| SOSSWORLD|This better be scarf\n|\n|t:|1666453172\n|switch|p2a: JON SNOW|Slowking, F|100\/100\n|move|p1a: Tapu Lele|Moonblast|p2a: JON SNOW\n|-damage|p2a: JON SNOW|72\/100\n|\n|-fieldend|move: Psychic Terrain\n|upkeep\n|turn|42\n|\n|t:|1666453192\n|move|p1a: Tapu Lele|Moonblast|p2a: JON SNOW\n|-damage|p2a: JON SNOW|42\/100\n|move|p2a: JON SNOW|Scald|p1a: Tapu Lele\n|-damage|p1a: Tapu Lele|42\/100\n|-status|p1a: Tapu Lele|brn\n|\n|-damage|p1a: Tapu Lele|36\/100 brn|[from] brn\n|upkeep\n|turn|43\n|\n|t:|1666453198\n|switch|p1a: Weavile|Weavile, F|43\/100\n|-ability|p1a: Weavile|Pressure\n|move|p2a: JON SNOW|Slack Off|p2a: JON SNOW\n|-heal|p2a: JON SNOW|92\/100\n|\n|upkeep\n|turn|44\n|\n|t:|1666453203\n|switch|p2a: VISERYS|Dragonite, M|29\/100\n|move|p1a: Weavile|Knock Off|p2a: VISERYS\n|-damage|p2a: VISERYS|0 fnt\n|-enditem|p2a: VISERYS|Heavy-Duty Boots|[from] move: Knock Off|[of] p1a: Weavile\n|faint|p2a: VISERYS\n|\n|upkeep\n|\n|t:|1666453205\n|switch|p2a: DRACARYS|Garchomp, M|78\/100\n|turn|45\n|j|%moondazing\n|c| 6yrOldBongWater|oh shit\n|c|\u2606Trogba Trogba|I hope to sweet jesus that this isn't tank\n|\n|t:|1666453231\n|move|p1a: Weavile|Knock Off|p2a: DRACARYS\n|-damage|p2a: DRACARYS|0 fnt\n|-damage|p1a: Weavile|31\/100|[from] ability: Rough Skin|[of] p2a: DRACARYS\n|-enditem|p2a: DRACARYS|Life Orb|[from] move: Knock Off|[of] p1a: Weavile\n|faint|p2a: DRACARYS\n|\n|upkeep\n|c|\u2606Trogba Trogba|gg\n|\n|t:|1666453235\n|switch|p2a: JON SNOW|Slowking, F|100\/100\n|turn|46\n|c| Reeynee|gg\n|\n|t:|1666453237\n|move|p1a: Weavile|Knock Off|p2a: JON SNOW\n|-supereffective|p2a: JON SNOW\n|-damage|p2a: JON SNOW|0 fnt\n|-enditem|p2a: JON SNOW|Heavy-Duty Boots|[from] move: Knock Off|[of] p1a: Weavile\n|faint|p2a: JON SNOW\n|\n|win|Trogba Trogba\n|n|\u2606Trogba Trogba|trogbatrogba\n|n|\u2606Schizo Shroomz|schizoshroomz\n|n| svenno|svenno\n|n| Mimikyu Stardust|mimikyustardust\n|n| Sww-Suwa|swwsuwa\n|n| Reeynee|reeynee\n|n| sufy512|sufy512\n|n| Down$pook|downpook\n|n| Faceblue|faceblue\n|n| 6yrOldBongWater|6yroldbongwater\n|n| SlothsWrath|slothswrath\n|n| GoatNoir|goatnoir\n|n| Paltham|paltham\n|n| SOSSWORLD|sossworld\n|n| fork you phil|forkyouphil\n|n|+moondazing|moondazing\n","uploadtime":1666453238,"views":23,"p1id":"trogbatrogba","p2id":"schizoshroomz","formatid":"gen8ou","rating":0,"private":0,"password":null}